locationtagger/__init__.py
locationtagger/locationextractor.py
locationtagger/utils.py
locationtagger/bin/locationtagger-nltk-spacy
locationtagger/data/City-Region-Locations.csv
locationtagger/data/diagram.jpg
locationtagger/data/words_to_ignore.csv
locationtagger/tests/__init__.py
locationtagger/tests/test_LocationExtractor.py
locationtagger/tests/test_NamedEntityExtractor.py
locationtagger-0.0.1.data/scripts/locationtagger-nltk-spacy
locationtagger-0.0.1.data/scripts/test_LocationExtractor.py
locationtagger-0.0.1.data/scripts/test_NamedEntityExtractor.py
locationtagger-0.0.1.dist-info/LICENSE
locationtagger-0.0.1.dist-info/METADATA
locationtagger-0.0.1.dist-info/WHEEL
locationtagger-0.0.1.dist-info/top_level.txt
locationtagger-0.0.1.dist-info/RECORD
