Metadata-Version: 2.1
Name: locationtagger
Version: 0.0.1
Summary: Detect & Extract locations from text or URL and find relationships among locations
Home-page: https://github.com/kaushiksoni10/locationtagger
Author: Kaushik Soni
Author-email: kaushiksoni10@gmail.com
License: MIT
Platform: UNKNOWN
Classifier: Programming Language :: Python :: 3
Classifier: License :: OSI Approved :: MIT License
Classifier: Natural Language :: English
Classifier: Topic :: Text Processing
Classifier: Operating System :: OS Independent
Requires-Python: >=3.5
